__init__.py
feather_ai/__init__.py
feather_ai/document.py
feather_ai/prompt.py
feather_ai/utils.py
feather_ai/agents/__init__.py
feather_ai/agents/agent.py
feather_ai/agents/base_agent.py
feather_ai/agents/loop_agent.py
feather_ai/agents/structured_streaming_agent.py
feather_ai/agents/subtask_agent.py
feather_ai/internal_utils/__init__.py
feather_ai/internal_utils/_exceptions.py
feather_ai/internal_utils/_image_gen.py
feather_ai/internal_utils/_multimodal.py
feather_ai/internal_utils/_provider.py
feather_ai/internal_utils/_structured_tool.py
feather_ai/internal_utils/_tools.py
feather_ai/internal_utils/_tracing.py
feather_ai/orchestration/__init__.py
feather_ai/rag_processors/__init__.py
feather_ai/rag_processors/_doc_convert.py
feather_ai/rag_processors/fast_processor.py
feather_ai/tools/__init__.py
feather_ai/tools/code_execution.py
feather_ai/tools/media.py
feather_ai/tools/media_async.py
feather_ai/tools/web.py
feather_ai/types/__init__.py
feather_ai/types/response.py
feather_ai_sdk-0.1.14.dist-info/METADATA
feather_ai_sdk-0.1.14.dist-info/WHEEL
feather_ai_sdk-0.1.14.dist-info/top_level.txt
feather_ai_sdk-0.1.14.dist-info/RECORD
