Metadata-Version: 2.4
Name: feather-ai-sdk
Version: 0.1.14
Summary: The lightest Agentic AI Framework you'll ever see
Author: Luca Bozzetti
Requires-Python: <3.14,>=3.9
Requires-Dist: langchain-google-genai>=3.1.0
Requires-Dist: langchain-openai>=1.0.3
Requires-Dist: langchain-anthropic>=1.1.0
Requires-Dist: langchain-mistralai>=1.0.1
Requires-Dist: langchain-deepseek>=1.0.1
Requires-Dist: tavily-python>=00.7.13
Requires-Dist: langchain-experimental>=0.4.0
Requires-Dist: requests
Requires-Dist: aiohttp
Requires-Dist: certifi
